aprile/POSE-pred.pt
aprile/__init__.py
aprile/model.py
aprile/pure_query.py
aprile/utils.py
aprile-0.1.0.data/data/POSE-pred.pt
aprile-0.1.0.dist-info/LICENSE
aprile-0.1.0.dist-info/METADATA
aprile-0.1.0.dist-info/WHEEL
aprile-0.1.0.dist-info/top_level.txt
aprile-0.1.0.dist-info/RECORD
