Metadata-Version: 2.1
Name: aprile
Version: 0.1.0
Summary: Adverse Polypharmacy Reaction Intelligent Learner and Explainer (APRILE) -- An explainable machine learning framework for exploring the molecular mechanisms of adverse drug reactions caused by polypharmacy (including disease, symptoms and mentel disorders).
Home-page: https://github.com/NYXFLOWER/APRILE
Author: Hao Xu
Author-email: nyx0flower@gmail.com
License: MIT License
Project-URL: Bug Tracker, https://github.com/NYXFLOWER/APRILE/issues
Project-URL: Documentation, https://aprile.readthedocs.io
Project-URL: Source, https://github.com/NYXFLOWER/APRILE/aprile
Keywords: machine learning,bioinformatics,graph neural network,adverse drug reaction,disease mechanism
Platform: UNKNOWN
Classifier: Intended Audience :: Developers
Classifier: Intended Audience :: Education
Classifier: Intended Audience :: Healthcare Industry
Classifier: Intended Audience :: Science/Research
Classifier: License :: OSI Approved :: MIT License
Classifier: Operating System :: OS Independent
Classifier: Programming Language :: Python :: 3
Classifier: Topic :: Scientific/Engineering :: Artificial Intelligence
Classifier: Topic :: Scientific/Engineering :: Medical Science Apps.
Classifier: Natural Language :: English
Requires-Python: >=3.7
License-File: LICENSE
Requires-Dist: scikit-learn (>=0.21.2)
Requires-Dist: scipy
Requires-Dist: matplotlib
Requires-Dist: networkx (>=2.4)
Requires-Dist: pandas
Requires-Dist: numpy
Requires-Dist: goatools
Requires-Dist: cython
